robot_controller/__init__.py
robot_controller/manipulators/__init__.py
robot_controller/manipulators/manipulator.py
robot_controller/manipulators/utils.py
robot_controller/manipulators/instances/__init__.py
robot_controller/manipulators/instances/ur3.py
robot_controller-0.2.dist-info/DESCRIPTION.rst
robot_controller-0.2.dist-info/METADATA
robot_controller-0.2.dist-info/RECORD
robot_controller-0.2.dist-info/WHEEL
robot_controller-0.2.dist-info/metadata.json
robot_controller-0.2.dist-info/top_level.txt
