Metadata-Version: 2.0
Name: robot-controller
Version: 0.2
Summary: A high-level framework for programming robotic arms using TCP/IP connection.
Home-page: UNKNOWN
Author: Michal Bednarek
Author-email: michal.bednarek@put.poznan.pl
License: MIT
Keywords: robotics,arm,manipulator,ur3,ur5,universal,robots
Platform: UNKNOWN
Requires-Dist: opencv-python (>=3.3.0.10)
Requires-Dist: numpy (>=1.12.0)
